plom_client-0.20.0.data/data/share/applications/org.plomgrading.PlomClient.desktop
plom_client-0.20.0.data/data/share/icons/hicolor/128x128/apps/org.plomgrading.PlomClient.png
plom_client-0.20.0.data/data/share/metainfo/org.plomgrading.PlomClient.metainfo.xml
plom_client-0.20.0.dist-info/licenses/LICENSE.md
plomclient/__init__.py
plomclient/aliceBob.py
plomclient/common.py
plomclient/demo_rubrics.toml
plomclient/feedback_rules.py
plomclient/misc_utils.py
plomclient/plom_exceptions.py
plomclient/rubric_utils.py
plomclient/rules.py
plomclient/tagging.py
plomclient/test_exceptions.py
plomclient/test_feedback_rules.py
plomclient/test_illadvised.py
plomclient/test_misc_utils.py
plomclient/test_print_score.py
plomclient/test_rubric_diff.py
plomclient/test_scoring.py
plomclient/test_tags.py
plomclient/tpv_utils.py
plomclient/version_maps.py
plomclient/client/__init__.py
plomclient/client/__main__.py
plomclient/client/about_dialog.py
plomclient/client/annotator.py
plomclient/client/backGrid.py
plomclient/client/chooser.py
plomclient/client/default_keys.toml
plomclient/client/downloader.py
plomclient/client/draw_operations.py
plomclient/client/elastics.py
plomclient/client/esdf_french_keys.toml
plomclient/client/identifier.py
plomclient/client/ijkl_keys.toml
plomclient/client/image_view_widget.py
plomclient/client/key_help.py
plomclient/client/key_wrangler.py
plomclient/client/marker.py
plomclient/client/pagecache.py
plomclient/client/pagerearranger.py
plomclient/client/pagescene.py
plomclient/client/pageview.py
plomclient/client/question_labels.py
plomclient/client/quota_dialogs.py
plomclient/client/randoIDer.py
plomclient/client/randoMarker.py
plomclient/client/random_identifying_utils.py
plomclient/client/random_marking_utils.py
plomclient/client/rubric_add_dialog.py
plomclient/client/rubric_conflict_dialog.py
plomclient/client/rubric_list.py
plomclient/client/rubric_other_usage_dialog.py
plomclient/client/tagging.py
plomclient/client/tagging_range_dialog.py
plomclient/client/task_model.py
plom_client-0.20.0.dist-info/METADATA
plom_client-0.20.0.dist-info/WHEEL
plom_client-0.20.0.dist-info/entry_points.txt
plom_client-0.20.0.dist-info/top_level.txt
plom_client-0.20.0.dist-info/RECORD
